fivetran_wrapper/__init__.py
fivetran_wrapper/constant_sets.py
fivetran_wrapper/fivetran_wrapper.py
fivetran_wrapper-0.1.2.dist-info/METADATA
fivetran_wrapper-0.1.2.dist-info/WHEEL
fivetran_wrapper-0.1.2.dist-info/top_level.txt
fivetran_wrapper-0.1.2.dist-info/RECORD
