Metadata-Version: 2.1
Name: fivetran-wrapper
Version: 0.1.2
Summary: Fivetran service API wrapper
Home-page: https://github.com/glavmotor/fivetraner
Author: Dmitry Kravtsov
License: MIT
Requires-Dist: requests (==2.*)
Requires-Dist: error-wrapper (==0.9.*)
